README.txt
setup.py
boois_vali_input/__init__.py
boois_vali_input/vali_input.py
boois_vali_input.egg-info/PKG-INFO
boois_vali_input.egg-info/SOURCES.txt
boois_vali_input.egg-info/dependency_links.txt
boois_vali_input.egg-info/requires.txt
boois_vali_input.egg-info/top_level.txt
boois_vali_input.egg-info/zip-safe